passwd/__init__.py
passwd-1.2.0.dist-info/LICENSE
passwd-1.2.0.dist-info/METADATA
passwd-1.2.0.dist-info/WHEEL
passwd-1.2.0.dist-info/top_level.txt
passwd-1.2.0.dist-info/RECORD
