Metadata-Version: 2.1
Name: passwd
Version: 1.2.0
Summary: Assorted utilities for gracefully handling and generating passwords
Home-page: https://github.com/bsoyka/passwd
Author: Benjamin Soyka
Author-email: bensoyka@icloud.com
License: UNKNOWN
Project-URL: Documentation, https://passwd.readthedocs.io/
Project-URL: Changelog, https://github.com/bsoyka/passwd/blob/master/CHANGELOG.md
Platform: UNKNOWN
Classifier: Programming Language :: Python :: 3
Classifier: License :: OSI Approved :: MIT License
Classifier: Operating System :: OS Independent
Requires-Python: >=3.6
Requires-Dist: requests (~=2.24.0)
